{"action":"index","controller":"Api::OembedController","params":{"url":"http://coub.com/view/4ac6","format":"json","controller":"api/oembed","action":"index"},"method":"GET","url":"/api/oembed.json?url=http%3A%2F%2Fcoub.com%2Fview%2F4ac6","records":[{"controller":"Api::OembedController","action":"index","params":{"url":"http://coub.com/view/4ac6","format":"json","controller":"api/oembed","action":"index"},"format":"json","method":"GET","path":"/api/oembed.json?url=http%3A%2F%2Fcoub.com%2Fview%2F4ac6","etype":"start_processing.action_controller","eduration":0.009221,"estart":1439918867.667458,"efinish":1439918867.667467},{"sql":"SELECT  \"coubs\".* FROM \"coubs\"  WHERE \"coubs\".\"permalink\" in ('4ac6', '6fa2') LIMIT 1","name":"Coub Load","connection_id":78021160,"binds":null,"connection_name":null,"etype":"sql.active_record","eduration":1.027164,"estart":1439918867.672921,"efinish":1439918867.673948},{"sql":"SELECT \"channels\".* FROM \"channels\"  WHERE \"channels\".\"id\" IN (2)","name":"Channel Load","connection_id":78021160,"binds":null,"connection_name":null,"etype":"sql.active_record","eduration":0.519156,"estart":1439918867.678128,"efinish":1439918867.678648},{"virtual_path":"coubs/_embed_code","etype":"!render_template.action_view","eduration":6.616993,"estart":1439918867.693577,"efinish":1439918867.700194},{"identifier":"/home/dev/TeamCity/work/c1cf20f9eaa9a53e/app/views/coubs/_embed_code.erb","etype":"render_partial.action_view","eduration":6.744176,"estart":1439918867.693532,"efinish":1439918867.700276},{"controller":"Api::OembedController","action":"index","params":{"url":"http://coub.com/view/4ac6","format":"json","controller":"api/oembed","action":"index"},"format":"json","method":"GET","path":"/api/oembed.json?url=http%3A%2F%2Fcoub.com%2Fview%2F4ac6","status":200,"view_runtime":0.303125,"db_runtime":1.54632,"etype":"process_action.action_controller","eduration":33.42883,"estart":1439918867.667741,"efinish":1439918867.70117}],"time":"2015-08-18T17:27:47+00:00","start":1439918867.667741,"end":1439918867.70117,"duration":33.42883,"gc_time":0.0,"event_name":"process_action.action_controller","meta":{"client_version":"0.0.6","rails_version":"3.2.22"}}
